vote/__init__.py
vote/apps.py
vote/conf.py
vote/pagination.py
vote/urls.py
vote/admin/__init__.py
vote/admin/votes.py
vote/management/__init__.py
vote/management/commands/__init__.py
vote/management/commands/bootstrap_vote.py
vote/migrations/0001_initial.py
vote/migrations/0002_votes_runoff.py
vote/migrations/__init__.py
vote/models/__init__.py
vote/models/base_result.py
vote/models/delegates.py
vote/models/electoral_votes.py
vote/models/votes.py
vote/serializers/__init__.py
vote/serializers/delegates.py
vote/serializers/electoral_votes.py
vote/serializers/votes.py
vote/utils/__init__.py
vote/utils/importers.py
vote/viewsets/__init__.py
vote/viewsets/base.py
vote/viewsets/delegates.py
vote/viewsets/electoral_votes.py
vote/viewsets/votes.py
politico_civic_vote-0.2.0.dist-info/LICENSE
politico_civic_vote-0.2.0.dist-info/METADATA
politico_civic_vote-0.2.0.dist-info/WHEEL
politico_civic_vote-0.2.0.dist-info/top_level.txt
politico_civic_vote-0.2.0.dist-info/RECORD
