Metadata-Version: 2.1
Name: politico-civic-vote
Version: 0.2.0
Summary: UNKNOWN
Home-page: https://github.com/The-Politico/politico-civic-vote
Author: POLITICO interactive news
Author-email: interactives@politico.com
License: MIT
Platform: UNKNOWN
Classifier: Development Status :: 3 - Alpha
Classifier: Intended Audience :: Developers
Classifier: Intended Audience :: Information Technology
Classifier: License :: OSI Approved :: MIT License
Classifier: Operating System :: OS Independent
Classifier: Programming Language :: Python :: 3
Classifier: Programming Language :: Python :: 3.5
Classifier: Programming Language :: Python :: 3.6
Classifier: Topic :: Internet :: WWW/HTTP
Requires-Dist: django
Requires-Dist: djangorestframework
Requires-Dist: dj-database-url
Requires-Dist: psycopg2
Requires-Dist: politico-civic-entity
Requires-Dist: politico-civic-geography
Requires-Dist: politico-civic-government
Requires-Dist: politico-civic-election
Provides-Extra: test
Requires-Dist: pytest; extra == 'test'
